dnnquant/__init__.py
dnnquant-0.0.1.dev0.dist-info/METADATA
dnnquant-0.0.1.dev0.dist-info/WHEEL
dnnquant-0.0.1.dev0.dist-info/top_level.txt
dnnquant-0.0.1.dev0.dist-info/RECORD
