Metadata-Version: 2.1
Name: dnnquant
Version: 0.0.1.dev0
Summary: dnnquant - quant library for DNN
Home-page: UNKNOWN
Author: Shadow Walker
License: UNKNOWN
Keywords: dnnquant
Platform: UNKNOWN
Classifier: Programming Language :: Python :: 3
Classifier: Programming Language :: Python :: 3.8
Classifier: Programming Language :: Python :: 3.9
Classifier: Programming Language :: Python :: 3.10
Requires-Dist: torch
